cirb
