Metadata-Version: 1.0
Name: cirb.blog
Version: 1.0a3
Summary: Blog project for CIRB
Home-page: https://github.com/CIRB/cirb.blog
Author: JeanMichel FRANCOIS aka toutpt
Author-email: toutpt@gmail.com
License: GPL
Keywords: plone blog
Platform: UNKNOWN
Classifier: Programming Language :: Python
Classifier: Framework :: Plone
Classifier: Framework :: Plone :: 4.0
Classifier: Framework :: Plone :: 4.1
Classifier: Framework :: Plone :: 4.2
